ZanQuery/ZanQuery.py
ZanQuery/__init__.py
ZanQuery/activate.py
ZanQuery-1.0.dist-info/LICENSE
ZanQuery-1.0.dist-info/METADATA
ZanQuery-1.0.dist-info/WHEEL
ZanQuery-1.0.dist-info/top_level.txt
ZanQuery-1.0.dist-info/RECORD
