Metadata-Version: 2.1
Name: ZanQuery
Version: 1.0
Summary: ZanQuery Query Language
Home-page: UNKNOWN
Author: Zanvok Corporation
License: UNKNOWN
Platform: UNKNOWN
Classifier: Programming Language :: Python :: 3
Classifier: License :: OSI Approved :: MIT License
Classifier: Operating System :: OS Independent
Requires-Python: >=3.7
License-File: LICENSE
